MANIFEST.in
README.md
requirements.txt
setup.py
dfr/Colour.py
dfr/__init__.py
dfr/abs_path.py
dfr/args.py
dfr/children_file.py
dfr/constant.py
dfr/files.py
dfr/find_last_modified_time.py
dfr/main.py
dfr/remover.py
dfr.egg-info/PKG-INFO
dfr.egg-info/SOURCES.txt
dfr.egg-info/dependency_links.txt
dfr.egg-info/entry_points.txt
dfr.egg-info/requires.txt
dfr.egg-info/top_level.txt
dfr/dependencies/__init__.py
dfr/dependencies/dependencies.py
dfr/dependencies/dependency.py
dfr/lib/__init__.py