Metadata-Version: 2.1
Name: dfr
Version: 0.0.3
Summary: A command line tool for finding and removing duplicacy
Home-page: http://github.com/srbcheema1/dfr
Author: Sarbjit Singh
Author-email: srbcheema1@gmail.com
License: MIT License
Platform: UNKNOWN
Classifier: Operating System :: POSIX :: Linux
Classifier: License :: OSI Approved :: MIT License
Classifier: Programming Language :: Python :: 3.5
